{
  "variants": {
    "": {
      "model": "srparasites:block/sepia_glass"
    }
  },
  "srparasites_legacy_variants": {
    "stage=0": {
      "model": "srparasites:sepia_glass"
    },
    "stage=1": {
      "model": "srparasites:sepia_glass"
    },
    "stage=2": {
      "model": "srparasites:sepia_glass"
    },
    "stage=3": {
      "model": "srparasites:sepia_glass"
    },
    "stage=4": {
      "model": "srparasites:sepia_glass"
    },
    "stage=5": {
      "model": "srparasites:sepia_glass"
    }
  }
}
